<annotation>
    <folder>bbox_xml_resized</folder>
    <filename>01 (2).jpg.xml</filename>
    <path>/Users/fenilsuchak/Desktop/Internship/For_yolo/bbox_xml_resized/01 (2).jpg.xml</path>
    <source>
        <database>Unknown</database>
    </source>
    <size>
        <width>512</width>
        <height>512</height>
        <depth>3</depth>
    </size>
    <segmented>0</segmented>
    <object>
        <name>0</name>
        <pose>Unspecified</pose>
        <truncated>0</truncated>
        <difficult>0</difficult>
        <bndbox>
            <xmin>130.52394366208</xmin>
            <ymin>271.84990619136</ymin>
            <xmax>373.543661971968</xmax>
            <ymax>433.23076923084795</ymax>
        </bndbox>
    </object>
</annotation>
