<annotation>
    <folder>bbox_xml_resized</folder>
    <filename>file (698).jpg.xml</filename>
    <path>/Users/fenilsuchak/Desktop/Internship/For_yolo/bbox_xml_resized/file (698).jpg.xml</path>
    <source>
        <database>Unknown</database>
    </source>
    <size>
        <width>512</width>
        <height>512</height>
        <depth>3</depth>
    </size>
    <segmented>0</segmented>
    <object>
        <name>0</name>
        <pose>Unspecified</pose>
        <truncated>0</truncated>
        <difficult>0</difficult>
        <bndbox>
            <xmin>71.99999999999999</xmin>
            <ymin>246.044444444416</ymin>
            <xmax>270.4</xmax>
            <ymax>472.17777777791997</ymax>
        </bndbox>
    </object>
</annotation>
