<annotation>
    <folder>bbox_xml_resized</folder>
    <filename>hyundai-i10-magnaowithsunroof-636606970143272773.jpg.xml</filename>
    <path>/Users/fenilsuchak/Desktop/Internship/For_yolo/bbox_xml_resized/hyundai-i10-magnaowithsunroof-636606970143272773.jpg.xml</path>
    <source>
        <database>Unknown</database>
    </source>
    <size>
        <width>512</width>
        <height>512</height>
        <depth>3</depth>
    </size>
    <segmented>0</segmented>
    <object>
        <name>0</name>
        <pose>Unspecified</pose>
        <truncated>0</truncated>
        <difficult>0</difficult>
        <bndbox>
            <xmin>0.0</xmin>
            <ymin>326.9674523007856</ymin>
            <xmax>493.6047904191617</xmax>
            <ymax>434.42424242424244</ymax>
        </bndbox>
    </object>
</annotation>
