<annotation>
    <folder>bbox_xml_resized</folder>
    <filename>media (130).jpg.xml</filename>
    <path>/Users/fenilsuchak/Desktop/Internship/For_yolo/bbox_xml_resized/media (130).jpg.xml</path>
    <source>
        <database>Unknown</database>
    </source>
    <size>
        <width>512</width>
        <height>512</height>
        <depth>3</depth>
    </size>
    <segmented>0</segmented>
    <object>
        <name>0</name>
        <pose>Unspecified</pose>
        <truncated>0</truncated>
        <difficult>0</difficult>
        <bndbox>
            <xmin>54.755555555555546</xmin>
            <ymin>273.06666666666666</ymin>
            <xmax>222.57777777777778</xmax>
            <ymax>402.962962962963</ymax>
        </bndbox>
    </object>
</annotation>
