<annotation>
    <folder>bbox_xml_resized</folder>
    <filename>media (101).jpg.xml</filename>
    <path>/Users/fenilsuchak/Desktop/Internship/For_yolo/bbox_xml_resized/media (101).jpg.xml</path>
    <source>
        <database>Unknown</database>
    </source>
    <size>
        <width>512</width>
        <height>512</height>
        <depth>3</depth>
    </size>
    <segmented>0</segmented>
    <object>
        <name>0</name>
        <pose>Unspecified</pose>
        <truncated>0</truncated>
        <difficult>0</difficult>
        <bndbox>
            <xmin>90.31111111111112</xmin>
            <ymin>210.48888888888888</ymin>
            <xmax>320.7111111111111</xmax>
            <ymax>395.3777777777778</ymax>
        </bndbox>
    </object>
</annotation>
