<annotation>
    <folder>bbox_xml_resized</folder>
    <filename>TH1YPHH_1419937_1_11363374.jpeg.xml</filename>
    <path>/Users/fenilsuchak/Desktop/Internship/For_yolo/bbox_xml_resized/TH1YPHH_1419937_1_11363374.jpeg.xml</path>
    <source>
        <database>Unknown</database>
    </source>
    <size>
        <width>512</width>
        <height>512</height>
        <depth>3</depth>
    </size>
    <segmented>0</segmented>
    <object>
        <name>0</name>
        <pose>Unspecified</pose>
        <truncated>0</truncated>
        <difficult>0</difficult>
        <bndbox>
            <xmin>159.36</xmin>
            <ymin>307.65410199556544</ymin>
            <xmax>350.08</xmax>
            <ymax>423.450110864745</ymax>
        </bndbox>
    </object>
</annotation>
