<annotation>
    <folder>bbox_xml_resized</folder>
    <filename>used_car_1483125_1526540683 dt.jpg.xml</filename>
    <path>/Users/fenilsuchak/Desktop/Internship/For_yolo/bbox_xml_resized/used_car_1483125_1526540683 dt.jpg.xml</path>
    <source>
        <database>Unknown</database>
    </source>
    <size>
        <width>512</width>
        <height>512</height>
        <depth>3</depth>
    </size>
    <segmented>0</segmented>
    <object>
        <name>0</name>
        <pose>Unspecified</pose>
        <truncated>0</truncated>
        <difficult>0</difficult>
        <bndbox>
            <xmin>359.8222222222222</xmin>
            <ymin>228.5037037037037</ymin>
            <xmax>511.2888888888889</xmax>
            <ymax>511.05185185185184</ymax>
        </bndbox>
    </object>
</annotation>
